hrenpack/__init__.py
hrenpack/algebra.py
hrenpack/argparse_plus.py
hrenpack/boolwork.py
hrenpack/charset.py
hrenpack/classes.py
hrenpack/clipboard_work.py
hrenpack/cmd.py
hrenpack/constants.py
hrenpack/date_and_time_work.py
hrenpack/decorators.py
hrenpack/encapsulation.py
hrenpack/filetype.py
hrenpack/functionwork.py
hrenpack/hashwork.py
hrenpack/i18n.py
hrenpack/ipwork.py
hrenpack/iterwork.py
hrenpack/kwargswork.py
hrenpack/listwork.py
hrenpack/mixins.py
hrenpack/network.py
hrenpack/numwork.py
hrenpack/print_color.py
hrenpack/python.py
hrenpack/resolution.py
hrenpack/slugwork.py
hrenpack/strwork.py
hrenpack/system.py
hrenpack/taskmgr.py
hrenpack/type_define.py
hrenpack/typings.py
hrenpack/windows_registry.py
hrenpack/custom_methods/__init__.py
hrenpack/filework/__init__.py
hrenpack/filework/source_code.py
hrenpack/filework/xml.py
hrenpack/framework/__init__.py
hrenpack/framework/pygame.py
hrenpack/framework/tkinter.py
hrenpack/framework/Pyside6/__init__.py
hrenpack/framework/Pyside6/templates.py
hrenpack/framework/Pyside6/variables.py
hrenpack/framework/Pyside6/widgets.py
hrenpack/framework/django/__init__.py
hrenpack/framework/django/db.py
hrenpack/framework/django/forms.py
hrenpack/framework/django/mixins.py
hrenpack/framework/django/urls.py
hrenpack/framework/django/views.py
hrenpack/framework/flask/__init__.py
hrenpack/framework/flask/mixins.py
hrenpack/framework/flask/forms/__init__.py
hrenpack/framework/flask/forms/fields.py
hrenpack/framework/flask/forms/mixins.py
hrenpack/framework/kivy/__init__.py
hrenpack/framework/kivy/commands.py
hrenpack/framework/kivy/image.py
hrenpack/framework/kivy/mixins.py
hrenpack/framework/kivy/screenmanager.py
hrenpack/framework/kivy/widgets/__init__.py
hrenpack/framework/kivy/widgets/box.py
hrenpack/framework/kivy/widgets/double.py
hrenpack/framework/kivy/widgets/dynamic.py
hrenpack/framework/kivy/widgets/font_percent.py
hrenpack/framework/kivy/widgets/input.py
hrenpack/framework/kivy/widgets/multi_screen_mode.py
hrenpack-2.5.5.dist-info/licenses/LICENSE
hrenpack-2.5.5.dist-info/METADATA
hrenpack-2.5.5.dist-info/WHEEL
hrenpack-2.5.5.dist-info/top_level.txt
hrenpack-2.5.5.dist-info/RECORD
